statebasedml/__init__.py
statebasedml/bitfold.py
statebasedml/data.py
statebasedml/myfunctions.py
statebasedml-1.0.0.dist-info/LICENSE
statebasedml-1.0.0.dist-info/METADATA
statebasedml-1.0.0.dist-info/WHEEL
statebasedml-1.0.0.dist-info/top_level.txt
statebasedml-1.0.0.dist-info/RECORD
