Metadata-Version: 2.1
Name: statebasedml
Version: 1.0.0
Summary: Train data with state based machine learning.
Home-page: https://github.com/bellemanwesley/statebasedml
Author: Wesley Belleman
Author-email: bellemanwesley@gmail.com
License: MIT
Platform: UNKNOWN
Classifier: Development Status :: 5 - Production/Stable
Classifier: Programming Language :: Python :: 3
Classifier: License :: OSI Approved :: MIT License
Classifier: Operating System :: OS Independent
Requires-Python: >=3.6
Requires-Dist: numpy
